<?xml version="1.0" encoding="UTF-8"?>
<skin>
<!-- 
See: /auxdata/docs/developer/contents/XmlUi.html
    -->
  <properties>
    <property
       name="view.size"
       value="150:150"/>
    <property
       name="icon.wait.wait"
       value="/ucar/unidata/idv/images/wait.gif"/>
    <property
       name="mcidasv.tab.title"
       value="4 View"/>
  </properties>
  <ui>
    <panel layout="border">
      <panel
         place="Center"
         layout="border">
        <panel
           layout="grid"
           cols="2"
           place="Center">
          <idv.view
             class="${view_class}"
             viewid="viewleft%version%"
             id="viewleft"
             properties="clickToFocus=true;shareViews=true;showControlLegend=false;size=%view.size%;shareGroup=view%versionuid%;"/>
          <idv.view
             class="${view_class}"
             viewid="viewright%version%"
             id="viewright"
             properties="clickToFocus=true;showToolBars=false;shareViews=true;showControlLegend=false;size=%view.size%;shareGroup=view%versionuid%;"/>
          <idv.view
             class="${view_class}"
             viewid="viewleft2%version%"
             id="viewleft2"
             properties="clickToFocus=true;shareViews=true;showControlLegend=false;size=%view.size%;shareGroup=view%versionuid%;"/>
          <idv.view
             class="${view_class}"
             viewid="viewright2%version%"
             id="viewright2"
             properties="clickToFocus=true;showToolBars=false;shareViews=true;showControlLegend=false;size=%view.size%;shareGroup=view%versionuid%;"/>
        </panel>
      </panel>
    </panel>
  </ui>
  <styles>
    <style
       class="iconbtn"
       space="2"
       mouse_enter="ui.setText(idv.messagelabel,prop:tooltip);ui.setBorder(this,etched);"
       mouse_exit="ui.setText(idv.messagelabel,);ui.setBorder(this,button);"/>
    <style
       class="textbtn"
       space="2"
       mouse_enter="ui.setText(idv.messagelabel,prop:tooltip)"
       mouse_exit="ui.setText(idv.messagelabel,)"/>
  </styles>
  <components/>
</skin>
